blindspin/__init__.py
blindspin-2.0.0.dist-info/DESCRIPTION.rst
blindspin-2.0.0.dist-info/METADATA
blindspin-2.0.0.dist-info/RECORD
blindspin-2.0.0.dist-info/WHEEL
blindspin-2.0.0.dist-info/metadata.json
blindspin-2.0.0.dist-info/top_level.txt
