Metadata-Version: 2.0
Name: blindspin
Version: 2.0.0
Summary: Braille Spinner for Click
Home-page: https://github.com/kennethreitz/blindspin
Author: Kennethreitz
Author-email: me@kennethreitz.org
License: MIT
Platform: UNKNOWN
Provides-Extra: test
Requires-Dist: click; extra == 'test'
Requires-Dist: pytest; extra == 'test'
Requires-Dist: six; extra == 'test'
